salmon/__init__.py
salmon/_version.py
salmon/utils.py
salmon/_out/__init__.py
salmon/backend/__init__.py
salmon/backend/core.py
salmon/backend/sampler.py
salmon/frontend/__init__.py
salmon/frontend/plotting.py
salmon/frontend/private.py
salmon/frontend/public.py
salmon/frontend/utils.py
salmon/frontend/static/__init__.py
salmon/triplets/__init__.py
salmon/triplets/manager.py
salmon/triplets/offline.py
salmon/triplets/test_config.py
salmon/triplets/samplers/__init__.py
salmon/triplets/samplers/_adaptive_runners.py
salmon/triplets/samplers/_random_sampling.py
salmon/triplets/samplers/_round_robin.py
salmon/triplets/samplers/_test_runner.py
salmon/triplets/samplers/_validation.py
salmon/triplets/samplers/utils.py
salmon/triplets/samplers/adaptive/__init__.py
salmon/triplets/samplers/adaptive/_embed.py
salmon/triplets/samplers/adaptive/_noise_models.py
salmon/triplets/samplers/adaptive/_score.py
salmon/triplets/samplers/adaptive/search/__init__.py
salmon/triplets/samplers/adaptive/search/__triplets.py
salmon/triplets/samplers/adaptive/search/_search.py
salmon/triplets/samplers/adaptive/search/gram_utils.py
salmon/triplets/samplers/adaptive/search/tests/__init__.py
salmon/triplets/samplers/adaptive/search/tests/test_gram_utils.py
salmon/triplets/samplers/adaptive/search/tests/test_search_refactor.py
salmon/triplets/samplers/adaptive/search/tests/test_uncertainty.py
salmon/triplets/samplers/adaptive/search/tests/utilsSTE.py
salmon/triplets/samplers/tests/__init__.py
salmon/triplets/samplers/tests/test_rr.py
tests/__init__.py
tests/test_active.py
tests/test_active_search.py
tests/test_allowabe_targets.py
tests/test_backend.py
tests/test_basic.py
tests/test_examples.py
tests/test_offline.py
tests/test_passive.py
tests/test_validation.py
tests/utils.py
salmon_triplets-1.0.3.dist-info/LICENSE.txt
salmon_triplets-1.0.3.dist-info/METADATA
salmon_triplets-1.0.3.dist-info/WHEEL
salmon_triplets-1.0.3.dist-info/top_level.txt
salmon_triplets-1.0.3.dist-info/RECORD
